azul_runner/__init__.py
azul_runner/binary_plugin.py
azul_runner/coordinator.py
azul_runner/local.py
azul_runner/log_setup.py
azul_runner/main.py
azul_runner/models.py
azul_runner/monitor.py
azul_runner/network.py
azul_runner/network_transform.py
azul_runner/plugin.py
azul_runner/plugin_executor.py
azul_runner/pusher.py
azul_runner/settings.py
azul_runner/storage.py
azul_runner/storage_spooled.py
azul_runner/test_utils/__init__.py
azul_runner/test_utils/test_template.py
azul_runner-9.0.38.dist-info/METADATA
azul_runner-9.0.38.dist-info/WHEEL
azul_runner-9.0.38.dist-info/top_level.txt
azul_runner-9.0.38.dist-info/RECORD
