Metadata-Version: 2.4
Name: azul-runner
Version: 9.0.38
Summary: Core framework for writing Python plugins for Azul.
Home-page: https://www.asd.gov.au/
Author: Azul
Author-email: azul@asd.gov.au
Classifier: Development Status :: 5 - Production/Stable
Classifier: License :: OSI Approved :: MIT License
Classifier: Programming Language :: Python
Classifier: Programming Language :: Python :: 3
Classifier: Programming Language :: Python :: 3.12
Classifier: Programming Language :: Python :: 3.13
Classifier: Programming Language :: Python :: 3.14
Classifier: Intended Audience :: Developers
Classifier: Topic :: Software Development :: Libraries
Requires-Python: >=3.12
Requires-Dist: azul-bedrock
Requires-Dist: bitarray>=0.9
Requires-Dist: cart
Requires-Dist: httpx
Requires-Dist: pydantic>2
Requires-Dist: pydantic-settings
Requires-Dist: watchdog
Requires-Dist: psutil
Provides-Extra: test-utils
Requires-Dist: azul-bedrock[test_utils]; extra == "test-utils"
Requires-Dist: black; extra == "test-utils"
Requires-Dist: fastapi; extra == "test-utils"
Requires-Dist: pytest; extra == "test-utils"
Requires-Dist: tox; extra == "test-utils"
Requires-Dist: uvicorn[standard]; extra == "test-utils"
Requires-Dist: pytest-timeout; extra == "test-utils"
Requires-Dist: yara-x; extra == "test-utils"
Requires-Dist: urllib3; extra == "test-utils"
Dynamic: author
Dynamic: author-email
Dynamic: classifier
Dynamic: description
Dynamic: description-content-type
Dynamic: home-page
Dynamic: provides-extra
Dynamic: requires-dist
Dynamic: requires-python
Dynamic: summary
